geogenie/__init__.py
geogenie/cli.py
geogenie/geogenie.py
geogenie/module_summary_script.py
geogenie/docs/source/conf.py
geogenie/models/__init__.py
geogenie/models/models.py
geogenie/optimize/bootstrap.py
geogenie/optimize/optuna_opt.py
geogenie/outliers/__init__.py
geogenie/outliers/detect_outliers.py
geogenie/plotting/__init__.py
geogenie/plotting/plotting.py
geogenie/samplers/interpolate.py
geogenie/samplers/samplers.py
geogenie/utils/__init__.py
geogenie/utils/argument_parser.py
geogenie/utils/callbacks.py
geogenie/utils/data.py
geogenie/utils/data_structure.py
geogenie/utils/exceptions.py
geogenie/utils/logger.py
geogenie/utils/loss.py
geogenie/utils/scorers.py
geogenie/utils/spatial_data_processors.py
geogenie/utils/transformers.py
geogenie/utils/utils.py
geogenie-1.0.2.dist-info/licenses/LICENSE.txt
geogenie-1.0.2.dist-info/METADATA
geogenie-1.0.2.dist-info/WHEEL
geogenie-1.0.2.dist-info/entry_points.txt
geogenie-1.0.2.dist-info/top_level.txt
geogenie-1.0.2.dist-info/RECORD
