Metadata-Version: 2.4
Name: GeoGenIE
Version: 1.0.2
Summary: Deep learning software package to predict geographic coordinates from genome-wide SNP data.
Author-email: "Bradley T. Martin, Ph.D." <evobio721@gmail.com>, "Tyler K. Chafin, Ph.D." <tkchafin@gmail.com>
License: GPL-3.0-only
Project-URL: Source Code, https://github.com/btmartin721/GeoGenIE
Project-URL: Bug Tracker, https://github.com/btmartin721/GenGenIE/issues
Keywords: Bioinformatics,AI,Deep Learning,GIS,Population Genetics,Landscape Genetics,Coordinates
Classifier: Development Status :: 4 - Beta
Classifier: Intended Audience :: Science/Research
Classifier: License :: OSI Approved :: GNU General Public License v3 (GPLv3)
Classifier: Natural Language :: English
Classifier: Programming Language :: Python :: 3
Classifier: Programming Language :: Python :: 3.11
Classifier: Programming Language :: Python :: 3.12
Classifier: Topic :: Scientific/Engineering :: Bio-Informatics
Classifier: Topic :: Scientific/Engineering :: GIS
Classifier: Topic :: Scientific/Engineering :: Information Analysis
Requires-Python: <3.13,>=3.11
License-File: LICENSE.txt
Requires-Dist: geopandas
Requires-Dist: geopy
Requires-Dist: imblearn
Requires-Dist: jenkspy
Requires-Dist: kaleido
Requires-Dist: kneed
Requires-Dist: matplotlib
Requires-Dist: numba
Requires-Dist: numpy
Requires-Dist: optuna
Requires-Dist: pandas
Requires-Dist: plotly
Requires-Dist: pykrige
Requires-Dist: pynndescent
Requires-Dist: pysam
Requires-Dist: pyyaml
Requires-Dist: requests
Requires-Dist: scikit-learn<=1.3.2
Requires-Dist: scipy
Requires-Dist: seaborn
Requires-Dist: statsmodels
Requires-Dist: torch
Requires-Dist: xgboost
Provides-Extra: dev
Requires-Dist: pdf2image; extra == "dev"
Requires-Dist: PyPDF2; extra == "dev"
Requires-Dist: pytest; extra == "dev"
Requires-Dist: snpio; extra == "dev"
Requires-Dist: sphinx; extra == "dev"
Requires-Dist: sphinx-rtd-theme; extra == "dev"
Requires-Dist: sphinxcontrib-napoleon; extra == "dev"
Requires-Dist: sphinxcontrib-bibtex; extra == "dev"
Requires-Dist: sphinx-autodoc-typehints; extra == "dev"
Requires-Dist: twine; extra == "dev"
Requires-Dist: wheel; extra == "dev"
Provides-Extra: docs
Requires-Dist: sphinx; extra == "docs"
Requires-Dist: sphinx-rtd-theme; extra == "docs"
Requires-Dist: sphinxcontrib-napoleon; extra == "docs"
Requires-Dist: sphinxcontrib-bibtex; extra == "docs"
Requires-Dist: sphinx-autodoc-typehints; extra == "docs"
Dynamic: license-file
